moneycounter/__init__.py
moneycounter/pnl.py
moneycounter-1.4.3.dist-info/METADATA
moneycounter-1.4.3.dist-info/WHEEL
moneycounter-1.4.3.dist-info/top_level.txt
moneycounter-1.4.3.dist-info/RECORD
