Metadata-Version: 2.4
Name: moneycounter
Version: 1.4.3
Summary: Portfolio Analytics Utilities
Author-email: Marc Schwarzschild <ms@TheBrookhavenGroup.com>
Maintainer-email: Marc Schwarzschild <ms@TheBrookhavenGroup.com>
License: MIT
Project-URL: homepage, https://github.com/schwarzschild/moneycounter
Project-URL: repository, https://github.com/schwarzschild/moneycounter
Project-URL: documentation, https://github.com/schwarzschild/moneycounter
Keywords: risk,fifo,money,investments
Classifier: Topic :: Office/Business :: Financial
Classifier: Topic :: Office/Business :: Financial :: Accounting
Classifier: Topic :: Office/Business :: Financial :: Investment
Requires-Python: >=3.7
Requires-Dist: pandas
Requires-Dist: pytz
